[{"N":"1500 GOLD WING","C":4},{"N":"750 MAGNA","C":3},{"N":"BIZ 100 ES","C":14},{"N":"BIZ 100 KS","C":3},{"N":"BIZ 110i","C":27},{"N":"BIZ 125 +","C":18},{"N":"BIZ 125 ES","C":119},{"N":"BIZ 125 EX","C":114},{"N":"BIZ 125 KS","C":20},{"N":"C 100 BIZ","C":7},{"N":"C 100 BIZ ES","C":7},{"N":"C 100 BIZ+","C":3},{"N":"CB 1000R","C":54},{"N":"CB 1000R ABS","C":67},{"N":"CB 1300 F SUPER FOUR","C":22},{"N":"CB 300R","C":359},{"N":"CB 300R ABS","C":33},{"N":"CB 400","C":19},{"N":"CB 400 FOUR","C":2},{"N":"CB 400 II","C":4},{"N":"CB 450","C":13},{"N":"CB 450 DX","C":11},{"N":"CB 450 E","C":1},{"N":"CB 450 TR","C":7},{"N":"CB 500","C":40},{"N":"CB 500 FOUR","C":5},{"N":"CB 500 X","C":25},{"N":"CB 500 X ABS","C":38},{"N":"CB 500F","C":46},{"N":"CB 500F ABS","C":20},{"N":"CB 550 FOUR","C":1},{"N":"CB 600F HORNET","C":222},{"N":"CB 650 F","C":20},{"N":"CB 650 F ABS","C":32},{"N":"CB 750 FOUR","C":5},{"N":"CB 750K","C":1},{"N":"CB TWISTER","C":50},{"N":"CB TWISTER ABS","C":6},{"N":"CBR 1000F","C":3},{"N":"CBR 1000RR","C":30},{"N":"CBR 1000RR FIREBLADE","C":112},{"N":"CBR 1000RR REPSOL","C":32},{"N":"CBR 1100XX SUPER BLACKBIRD","C":7},{"N":"CBR 250R","C":31},{"N":"CBR 450","C":1},{"N":"CBR 450 SR","C":16},{"N":"CBR 500R","C":24},{"N":"CBR 500R ABS","C":25},{"N":"CBR 600F","C":101},{"N":"CBR 600RR","C":115},{"N":"CBR 600RR ABS","C":1},{"N":"CBR 650F","C":18},{"N":"CBR 650F ABS","C":12},{"N":"CBR 900RR","C":3},{"N":"CBR 900RR FIREBLADE","C":8},{"N":"CBR 954RR FIREBLADE","C":2},{"N":"CBX 150 AERO","C":1},{"N":"CBX 200 STRADA","C":8},{"N":"CBX 250 TWISTER","C":108},{"N":"CBX 750 FOUR","C":22},{"N":"CBX 750 FOUR INDY","C":7},{"N":"CG 125","C":11},{"N":"CG 125 CARGO ES","C":2},{"N":"CG 125 CARGO KS","C":9},{"N":"CG 125 FAN","C":21},{"N":"CG 125 FAN ES","C":58},{"N":"CG 125 FAN ESD","C":9},{"N":"CG 125 FAN KS","C":109},{"N":"CG 125 ML","C":3},{"N":"CG 125 TITAN","C":4},{"N":"CG 125 TITAN ES","C":2},{"N":"CG 125 TITAN KS","C":14},{"N":"CG 125 TITAN KSE","C":4},{"N":"CG 125 TODAY","C":2},{"N":"CG 125i CARGO","C":4},{"N":"CG 125i FAN","C":30},{"N":"CG 150 CARGO ESD","C":2},{"N":"CG 150 FAN","C":2},{"N":"CG 150 FAN ESDi","C":132},{"N":"CG 150 FAN ESI","C":72},{"N":"CG 150 JOB","C":6},{"N":"CG 150 SPORT","C":3},{"N":"CG 150 START ES","C":16},{"N":"CG 150 TITAN ES","C":21},{"N":"CG 150 TITAN ESD","C":49},{"N":"CG 150 TITAN EX","C":44},{"N":"CG 150 TITAN KS","C":37},{"N":"CG 150 TITAN MIX ES","C":9},{"N":"CG 150 TITAN MIX ESD","C":25},{"N":"CG 150 TITAN MIX EX","C":48},{"N":"CG 150 TITAN MIX KS","C":3},{"N":"CG 160 CARGO","C":8},{"N":"CG 160 FAN","C":40},{"N":"CG 160 START ES","C":26},{"N":"CG 160 TITAN ESDi","C":7},{"N":"CG 160 TITAN EX","C":35},{"N":"CR 80","C":1},{"N":"CRF 1000L AFRICA TWIN ABS","C":10},{"N":"CRF 1000L AFRICA TWIN ABS TE","C":8},{"N":"CRF 150F","C":5},{"N":"CRF 230F","C":43},{"N":"CRF 250L","C":2},{"N":"CRF 250R","C":5},{"N":"CRF 250X","C":5},{"N":"CRF 450R","C":8},{"N":"CRF 450X","C":3},{"N":"CTX 700N ABS","C":3},{"N":"GL 1800 GOLD WING","C":14},{"N":"GL 1800 GOLD WING 40TH ANNIVERSARY EDITION","C":1},{"N":"LEAD 110","C":66},{"N":"NC 700X","C":32},{"N":"NC 700X ABS","C":5},{"N":"NC 750X","C":4},{"N":"NC 750X ABS","C":20},{"N":"NX 150","C":1},{"N":"NX 350 SAHARA","C":11},{"N":"NX 400i FALCON","C":23},{"N":"NX4 FALCON","C":91},{"N":"NXR 125 BROS ES","C":11},{"N":"NXR 125 BROS KS","C":5},{"N":"NXR 150 BROS ES","C":47},{"N":"NXR 150 BROS ESD","C":42},{"N":"NXR 150 BROS KS","C":4},{"N":"NXR 150 BROS MIX ES","C":11},{"N":"NXR 150 BROS MIX ESD","C":45},{"N":"NXR 150 BROS MIX KS","C":6},{"N":"NXR 160 BROS","C":12},{"N":"NXR 160 BROS ESD","C":12},{"N":"NXR 160 BROS ESDD","C":38},{"N":"PCX","C":126},{"N":"PCX DLX","C":35},{"N":"POP 100","C":7},{"N":"POP 110i","C":11},{"N":"SH 150i","C":2},{"N":"SH 300i","C":23},{"N":"SHADOW 1100 AC","C":1},{"N":"SHADOW 1100 AERO","C":2},{"N":"SHADOW 600C VT","C":44},{"N":"SHADOW 750","C":116},{"N":"ST 1100 PAN EUROPEAN","C":2},{"N":"SUPER HAWK 1000","C":1},{"N":"TRX 420 FOURTRAX 4X4","C":11},{"N":"VALKYRIE 1500","C":3},{"N":"VFR 1200F","C":18},{"N":"VFR 1200X","C":6},{"N":"VTX 1800C","C":3},{"N":"XL 1000V VARADERO","C":19},{"N":"XL 125 DUTY","C":1},{"N":"XL 125S","C":1},{"N":"XL 250R","C":1},{"N":"XL 700V TRANSALP","C":46},{"N":"XL 700V TRANSALP ABS","C":22},{"N":"XLR 125","C":2},{"N":"XLR 125 ES","C":1},{"N":"XLX 250R","C":4},{"N":"XLX 350R","C":6},{"N":"XR 200R","C":1},{"N":"XR 250 TORNADO","C":38},{"N":"XRE 190 ABS","C":19},{"N":"XRE 300","C":260},{"N":"XRE 300 ABS","C":33},{"N":"XRE 300 ADVENTURE","C":4}]