[{"N":"CRYPTON 100","C":1},{"N":"CRYPTON ED","C":10},{"N":"CRYPTON K","C":14},{"N":"DRAG STAR 650","C":106},{"N":"DT 180","C":1},{"N":"DT 180Z","C":7},{"N":"DT 200","C":1},{"N":"DT 200R","C":2},{"N":"FACTOR 150 E","C":12},{"N":"FACTOR 150 ED","C":21},{"N":"FACTOR YBR 125 E","C":3},{"N":"FACTOR YBR 125 ED","C":23},{"N":"FACTOR YBR 125 ED BLACK EDITION","C":2},{"N":"FACTOR YBR 125 K","C":13},{"N":"FACTOR YBR 125 K1","C":15},{"N":"FAZER 250IE LIMITED EDITION","C":15},{"N":"FAZER 600S","C":12},{"N":"FAZER BLACK EDITION","C":2},{"N":"FAZER FZ6S","C":8},{"N":"FAZER YS 150 ED","C":41},{"N":"FAZER YS 150 SED","C":51},{"N":"FAZER YS 250","C":193},{"N":"FAZER YS 250 BLUEFLEX","C":81},{"N":"FZ1","C":1},{"N":"FZ1 FAZER","C":1},{"N":"FZ6N","C":28},{"N":"FZ8","C":1},{"N":"GRIZZLY 660","C":1},{"N":"MIDNIGHT WARRIOR","C":1},{"N":"MT-01","C":8},{"N":"MT-03","C":56},{"N":"MT-03 ABS","C":9},{"N":"MT-07","C":33},{"N":"MT-07 ABS","C":22},{"N":"MT-09","C":48},{"N":"MT-09 SP","C":9},{"N":"MT-09 TRACER","C":16},{"N":"NEO AT 115","C":12},{"N":"NEO CVT 115","C":5},{"N":"NMAX 160 ABS","C":26},{"N":"RD 135","C":4},{"N":"RD 350 LC","C":1},{"N":"RD 350R","C":2},{"N":"RD 50","C":1},{"N":"ROYAL STAR 1300","C":5},{"N":"RX 180","C":1},{"N":"T115 CRYPTON ED","C":3},{"N":"T115 CRYPTON K","C":3},{"N":"TDM 225","C":3},{"N":"TDM 850","C":6},{"N":"TDM 900","C":15},{"N":"TMAX","C":3},{"N":"TT-R 125","C":1},{"N":"TT-R 125LE","C":1},{"N":"TT-R 125LWE","C":1},{"N":"TT-R 230","C":6},{"N":"V MAX","C":1},{"N":"V MAX 1200","C":12},{"N":"VIRAGO XV 535","C":7},{"N":"WR 250","C":4},{"N":"WR 450F","C":2},{"N":"XJ6 F","C":46},{"N":"XJ6 F ABS","C":2},{"N":"XJ6 F RACING BLUE","C":4},{"N":"XJ6 N","C":112},{"N":"XJ6 N ABS","C":11},{"N":"XJ6 N ABS SP","C":5},{"N":"XJ6 N SP","C":6},{"N":"XT 225","C":3},{"N":"XT 600 E","C":40},{"N":"XT 600 Z TÉNÉRÉ","C":7},{"N":"XT 660 R","C":138},{"N":"XT 660 Z TÉNÉRÉ","C":35},{"N":"XT 660 Z TÉNÉRÉ ABS","C":6},{"N":"XT1200Z SUPER TÉNÉRÉ","C":46},{"N":"XT1200Z SUPER TÉNÉRÉ DX","C":15},{"N":"XTZ 125 E","C":14},{"N":"XTZ 125 K","C":4},{"N":"XTZ 125 XE","C":12},{"N":"XTZ 125 XK","C":2},{"N":"XTZ 250 LANDER","C":102},{"N":"XTZ 250 TÉNÉRÉ","C":121},{"N":"XTZ 250 TÉNÉRÉ BLUEFLEX","C":29},{"N":"XTZ 250 X","C":15},{"N":"XTZ 750S TENERE","C":12},{"N":"XTZ CROSSER 150 E","C":5},{"N":"XTZ CROSSER 150 ED","C":53},{"N":"XV 1100 VIRAGO","C":2},{"N":"XV 250 VIRAGO","C":2},{"N":"XV 250S VIRAGO","C":10},{"N":"XV 535S VIRAGO","C":3},{"N":"XV VIRAGO 750","C":2},{"N":"XVS 950A MIDNIGHT STAR","C":78},{"N":"YBR 125 E","C":2},{"N":"YBR 125 ED","C":1},{"N":"YBR 125 FACTOR ED","C":8},{"N":"YBR 125 FACTOR K","C":4},{"N":"YBR 125K","C":6},{"N":"YFM 350R","C":2},{"N":"YFZ 450","C":2},{"N":"YZF-R1","C":150},{"N":"YZF-R3","C":40},{"N":"YZF-R3 ABS","C":8},{"N":"YZF-R6","C":53}]